vcfiscal/__init__.py
vcfiscal/resources.py
vcfiscal/subsystem/__init__.py
vcfiscal/subsystem/parametrizacao/__init__.py
vcfiscal/subsystem/parametrizacao/cest/__init__.py
vcfiscal/subsystem/parametrizacao/cest/resource.py
vcfiscal/subsystem/parametrizacao/cfop/__init__.py
vcfiscal/subsystem/parametrizacao/cfop/resource.py
vcfiscal/subsystem/parametrizacao/domain_fiscal/__init__.py
vcfiscal/subsystem/parametrizacao/domain_fiscal/resource.py
vcfiscal/subsystem/parametrizacao/ibpt/__init__.py
vcfiscal/subsystem/parametrizacao/ibpt/resource.py
vcfiscal/subsystem/parametrizacao/ibpt_ncm/__init__.py
vcfiscal/subsystem/parametrizacao/ibpt_ncm/resource.py
vcfiscal/subsystem/parametrizacao/ncm/__init__.py
vcfiscal/subsystem/parametrizacao/ncm/resource.py
vcfiscal/subsystem/parametrizacao/ncm_cest/__init__.py
vcfiscal/subsystem/parametrizacao/ncm_cest/resource.py
vcfiscal/subsystem/parametrizacao/operacao_fiscal/__init__.py
vcfiscal/subsystem/parametrizacao/operacao_fiscal/resource.py
vcfiscal/subsystem/parametrizacao/regime_tributario/__init__.py
vcfiscal/subsystem/parametrizacao/regime_tributario/resource.py
vcfiscal/subsystem/sysadmin/__init__.py
vcfiscal/subsystem/sysadmin/arquivo_ibpt/__init__.py
vcfiscal/subsystem/sysadmin/arquivo_ibpt/controller.py
vcfiscal/subsystem/sysadmin/arquivo_ibpt/manager.py
vcfiscal/subsystem/sysadmin/arquivo_ibpt/resource.py
vcfiscal/subsystem/sysadmin/arquivo_ibpt/tasks.py
vcfiscal/subsystem/sysadmin/arquivo_sync/__init__.py
vcfiscal/subsystem/sysadmin/arquivo_sync/controller.py
vcfiscal/subsystem/sysadmin/arquivo_sync/manager.py
vcfiscal/subsystem/sysadmin/arquivo_sync/resource.py
vcfiscal/subsystem/sysadmin/arquivo_sync/tasks.py
vcfiscal/subsystem/sysadmin/ibpt_sync/__init__.py
vcfiscal/subsystem/sysadmin/ibpt_sync/manager.py
vcfiscal/subsystem/sysadmin/ibpt_sync/resource.py
vcfiscal/subsystem/sysadmin/ibpt_sync/sync_manager.py
vcfiscal-1.0.0.dist-info/AUTHORS
vcfiscal-1.0.0.dist-info/METADATA
vcfiscal-1.0.0.dist-info/WHEEL
vcfiscal-1.0.0.dist-info/top_level.txt
vcfiscal-1.0.0.dist-info/RECORD
